statespace/__init__.py
statespace/__main__.py
statespace/models/__init__.py
statespace/models/base_model.py
statespace/models/bearings_only.py
statespace/models/one_state.py
statespace/models/three_state.py
statespace/processors/__init__.py
statespace/processors/extended_kalman_filter.py
statespace/processors/particle_filter.py
statespace/processors/sigma_point_kalman_filter.py
statespace/processors/simplex_linear_programming.py
statespace-1.6.3.dist-info/METADATA
statespace-1.6.3.dist-info/WHEEL
statespace-1.6.3.dist-info/RECORD
